editwheel/__init__.py
editwheel/cli.py
editwheel/editwheel.cpython-312-aarch64-linux-gnu.so
editwheel-0.2.3.dist-info/METADATA
editwheel-0.2.3.dist-info/WHEEL
editwheel-0.2.3.dist-info/entry_points.txt
editwheel-0.2.3.dist-info/licenses/LICENSE
editwheel-0.2.3.dist-info/RECORD
